{
  "evidence": {
    "journal": {
      "files": [
        "Journal.2025-12-08T213814.01.log"
      ],
      "first_seen_utc": "2025-12-08T20:54:29Z",
      "last_seen_utc": "2025-12-08T20:54:35Z"
    },
    "method": "elite_journal"
  },
  "features": {
    "bodies": {
      "fss_bodycount": 23,
      "fss_nonbodycount": 9,
      "has_gas_giant": false,
      "has_ringed_body": true,
      "n_bodies_scanned": 2,
      "n_gas_giants": 0,
      "n_planets_scanned": 1,
      "n_ringed_bodies": 1,
      "n_terraformables": 0,
      "planet_classes": [
        "Metal rich body"
      ]
    },
    "signals": {
      "n_fss_body_signals_events": 0,
      "n_saa_mappings": 0
    },
    "stars": {
      "n_stars": 1,
      "types": [
        "G"
      ]
    }
  },
  "label": "non_click",
  "provenance": {
    "generated_at_utc": "2026-02-16T15:20:47.879268Z",
    "generated_by": "tools/extract_non_click_systems.py"
  },
  "schema_version": 1,
  "system": {
    "address": 113271359715,
    "name": "Oochoss HS-H d11-3",
    "star_pos": [
      -1411.59375,
      -30.8125,
      -1332.65625
    ]
  }
}